tombstone/__init__.py
tombstone/tombstone.py
tombstone-0.1.1.dist-info/licenses/LICENSE
tombstone-0.1.1.dist-info/METADATA
tombstone-0.1.1.dist-info/WHEEL
tombstone-0.1.1.dist-info/top_level.txt
tombstone-0.1.1.dist-info/RECORD
